vpk_custom_functions/__init__.py
vpk_custom_functions/main.py
vpk_custom_functions-0.1.1.dist-info/LICENSE
vpk_custom_functions-0.1.1.dist-info/METADATA
vpk_custom_functions-0.1.1.dist-info/WHEEL
vpk_custom_functions-0.1.1.dist-info/top_level.txt
vpk_custom_functions-0.1.1.dist-info/RECORD
