Metadata-Version: 2.1
Name: vpk_custom_functions
Version: 0.1.1
Summary: Contains custom functions which are used repeatedly during development
Home-page: https://github.com/vishnuprksh/vpk_custom_functions
Download-URL: https://github.com/vishnuprksh/vpk_custom_functions/archive/refs/tags/0.0.1.tar.gz
Author: Vishnu Prakash
Author-email: vishnucheppanam@gmail.com
Classifier: Programming Language :: Python :: 3
Classifier: License :: OSI Approved :: MIT License
Classifier: Operating System :: OS Independent
Requires-Python: >=3.6
License-File: LICENSE
Requires-Dist: IPython
Requires-Dist: pandas
